Youtube2Images/you2img.py
Youtube2Images-1.1.0.dist-info/LICENSE
Youtube2Images-1.1.0.dist-info/METADATA
Youtube2Images-1.1.0.dist-info/WHEEL
Youtube2Images-1.1.0.dist-info/top_level.txt
Youtube2Images-1.1.0.dist-info/RECORD
