Metadata-Version: 2.1
Name: Youtube2Images
Version: 1.1.0
Summary: Python Package to Convert youtube vieo to images frames
Home-page: https://iraqprogrammer.wordpress.com/
Author: Falah.G.Saleh
Author-email: falahgs07@gmail.com
License: UNKNOWN
Keywords: yuotube,images,dataset images
Platform: UNKNOWN
Classifier: Programming Language :: Python :: 3
Classifier: Programming Language :: Python :: 3.5
Classifier: Programming Language :: Python :: 3.6
Classifier: Programming Language :: Python :: 3.7
Classifier: Programming Language :: Python :: 3.8
Classifier: License :: OSI Approved :: MIT License
Classifier: Operating System :: OS Independent
Requires-Python: >=3.6
Requires-Dist: pytube3
Requires-Dist: opencv-python
